telebaka_lprmerch_poll/__init__.py
telebaka_lprmerch_poll/admin.py
telebaka_lprmerch_poll/bot.py
telebaka_lprmerch_poll/models.py
telebaka_lprmerch_poll/migrations/0001_initial.py
telebaka_lprmerch_poll/migrations/0002_polluser_accepting_custom.py
telebaka_lprmerch_poll/migrations/__init__.py
telebaka_lprmerch_poll-0.1.0.dist-info/METADATA
telebaka_lprmerch_poll-0.1.0.dist-info/RECORD
telebaka_lprmerch_poll-0.1.0.dist-info/WHEEL
telebaka_lprmerch_poll-0.1.0.dist-info/top_level.txt
